pycowsay_rich/__init__.py
pycowsay_rich/talk.py
pycowsay_rich-0.1.4.dist-info/entry_points.txt
pycowsay_rich-0.1.4.dist-info/LICENSE
pycowsay_rich-0.1.4.dist-info/WHEEL
pycowsay_rich-0.1.4.dist-info/METADATA
pycowsay_rich-0.1.4.dist-info/RECORD
