Metadata-Version: 2.1
Name: pycowsay-rich
Version: 0.1.4
Summary: A rich version of pycowsay!
Home-page: https://codeberg.org/KybernetikJo/pycowsay-rich
Author: Johannes Kaisinger
Requires-Python: >=3.8,<4.0
Classifier: Programming Language :: Python :: 3
Classifier: Programming Language :: Python :: 3.8
Classifier: Programming Language :: Python :: 3.9
Classifier: Programming Language :: Python :: 3.10
Classifier: Programming Language :: Python :: 3.11
Requires-Dist: rich (>=11.0.0)
